{
  "album_filter": {
    "sort": null
  },
  "albums_page": {
    "title": "Album"
  },
  "general": {
    "action": {
      "delete": "Elimina",
      "more": "Altro"
    },
    "loading": {
      "media": "Caricamento media",
      "timeline": "Caricamento timeline"
    }
  },
  "header": {
    "search": {
      "result_type": {
        "media": null,
        "photos": "Foto"
      }
    }
  },
  "people_page": {
    "action_label": {
      "change_label": null,
      "detach_face": null,
      "merge_face": null,
      "move_faces": null
    },
    "face_group": {
      "action": {
        "add_label": "Aggiungi etichetta",
        "change_label": "Cambia etichetta",
        "detach_face": "Separa volto",
        "merge_face": "Unisci volto",
        "move_faces": "Sposta volti"
      }
    },
    "modal": {
      "merge_people_groups": {
        "description": "Tutte le immagini di questo volto saranno unite alle immagini del volto selezionato",
        "destination_table": {
          "title": "Seleziona il volto di destinazione"
        },
        "title": "Unisci immagini volto"
      }
    },
    "table": {
      "select_face_group": {
        "search_faces_placeholder": "Cerca volti..."
      },
      "select_image_faces": {
        "search_images_placeholder": "Cerca immagini..."
      }
    },
    "tableselect_face_group": {
      "search_faces_placeholder": null
    },
    "tableselect_image_faces": {
      "search_images_placeholder": null
    }
  },
  "settings": {
    "users": {
      "table": {
        "column_names": {
          "admin": "Admin",
          "capabilities": null
        }
      }
    }
  },
  "share_page": {
    "protected_share": {
      "password_required_error": null
    }
  },
  "sidebar": {
    "album": {
      "album_cover": null,
      "cover_photo": "",
      "reset_cover": null,
      "set_cover": null,
      "title": "Opzioni Album",
      "title_placeholder": null
    },
    "download": {
      "filesize": {
        "byte": "{{count}} Byte",
        "byte_plural": "{{count}} Bytes",
        "giga_byte": "{{count}} GB",
        "giga_byte_plural": "",
        "kilo_byte": "{{count}} KB",
        "kilo_byte_plural": "",
        "mega_byte": "{{count}} MB",
        "mega_byte_plural": "",
        "tera_byte": "{{count}} TB",
        "tera_byte_plural": ""
      }
    },
    "media": {
      "album": ""
    },
    "sharing": {
      "delete": null,
      "more": null,
      "table_header": "Condivisioni pubbliche"
    }
  },
  "timeline_filter": {
    "date": {
      "dropdown_all": null,
      "label": null
    }
  }
}
